pluto
test
