Metadata-Version: 1.2
Name: Operation-Pluto
Version: 0.1.1
Summary: Grab and rinse financial and economic data.
Home-page: https://github.com/hydra-lab/Operation-Pluto
Author: Operation Pluto contributors
Author-email: UNKNOWN
License: AGPL-3.0
Keywords: data-pipeline finance market
Platform: UNKNOWN
Classifier: Topic :: Office/Business :: Financial :: Investment
Classifier: Programming Language :: Python :: 3.5
Classifier: Development Status :: 2 - Pre-Alpha
Requires-Python: >=3.5
